everywhere/__init__.py
everywhere/base.py
python_everywhere-0.1.0.dist-info/DESCRIPTION.rst
python_everywhere-0.1.0.dist-info/METADATA
python_everywhere-0.1.0.dist-info/RECORD
python_everywhere-0.1.0.dist-info/WHEEL
python_everywhere-0.1.0.dist-info/metadata.json
python_everywhere-0.1.0.dist-info/top_level.txt
