Metadata-Version: 2.0
Name: python-everywhere
Version: 0.1.0
Summary: A template project for Python
Home-page: https://github.com/wdv4758h/python-everywhere
Author: Chiu-Hsiang Hsu
Author-email: wdv4758h@gmail.com
License: BSD
Download-URL: https://github.com/wdv4758h/python-everywhere/archive/v0.1.0.zip
Platform: UNKNOWN
Classifier: Development Status :: 2 - Pre-Alpha
Classifier: Environment :: Console
Classifier: Intended Audience :: Developers
Classifier: License :: OSI Approved :: BSD License
Classifier: Operating System :: OS Independent
Classifier: Programming Language :: Python
Classifier: Programming Language :: Python :: 3
Classifier: Programming Language :: Python :: 3.4
Classifier: Programming Language :: Python :: 3.5
